vaspanalyse/__init__.py
vaspanalyse/__main__.py
vaspanalyse/parser.py
vaspanalyse/results.py
vaspanalyse-0.1.0.dist-info/METADATA
vaspanalyse-0.1.0.dist-info/WHEEL
vaspanalyse-0.1.0.dist-info/entry_points.txt
vaspanalyse-0.1.0.dist-info/top_level.txt
vaspanalyse-0.1.0.dist-info/RECORD
